{
  "title": "Sensor",
  "publicationStatus": "draft",
  "subtitle": "Testing the Sensor model type",
  "about": "",
  "models": [
    {
      "type": "sensor",
      "id": "signal1",
      "url": "models/sensor/sensor.json",
      "viewOptions": {
        "controlButtons": "",
        "showClock": true
      },
      "onLoad": [
        "function setButtonState() {",
        "  setComponentDisabled('start-button', !get('isPlayable'));",
        "  setComponentDisabled('stop-button', get('isStopped'));",
        "  setComponentDisabled('new-run-button', !get('hasPlayed'));",
        "}",
        "onPropertyChange('isPlayable', setButtonState);",
        "onPropertyChange('isStopped', setButtonState);",
        "onPropertyChange('hasPlayed', setButtonState);",
        "setButtonState();"
      ]
    }
  ],
  "components": [
    {
      "type": "graph",
      "id": "propertiesGraph",
      "title": "Sensor Reading",
      "xlabel": "Time (s)",
      "ymin": 0,
      "ymax": 6,
      "xmax": 30,
      "xTickCount": 6,
      "xFormatter": ".2s",
      "yFormatter": ".2s",
      "properties": [
        "sensorReading"
      ]
    },
    {
      "type": "button",
      "id": "start-button",
      "text": "Start",
      "tooltip": "Start the experiment run.",
      "action": [
        "start();"
      ]
    },
    {
      "type": "button",
      "id": "stop-button",
      "text": "Stop",
      "tooltip": "Stop the experiment run.",
      "action": [
        "stop();"
      ]
    },
    {
      "type": "button",
      "id": "new-run-button",
      "text": "New Run",
      "tooltip": "Set up a new experiment run.",
      "action": [
        "reset({",
        "  retainParameters: ['sensorType'],",
        "  cause: 'new-run'",
        "});"
      ]
    },
    {
      "type": "button",
      "id": "reset-button",
      "text": "Reset",
      "tooltip": "Reset the sensor.",
      "action": [
        "reload();"
      ]
    }
  ],
  "layout": {
    "below-model": [
      "propertiesGraph"
    ],
    "container-bottom": [
      "start-button",
      "stop-button",
      "new-run-button",
      "reset-button"
    ]
  },
  "exports": {
    "perRun": ["sensorType"],
    "perTick": ["sensorReading"]
  },
  "template": [
    {
      "id": "below-model",
      "top": "model.bottom",
      "width": "model.width",
      "height": "0.7 * model.width"
    },
    {
      "id": "container-bottom",
      "top": "below-model.bottom",
      "width": "model.width"
    }
  ]
}