{
  "temperature_control": false,
  "width": 4,
  "height": 2.5,
  "viscosity": 0,
  "keShading": false,
  "chargeShading": false,
  "showVDWLines": false,
  "VDWLinesRatio": 2,
  "gravitationalField": false,
  "showClock": false,
  "viewRefreshInterval": 50,
  "timeStep": 1,
  "elements": [
    {
      "id": 0,
      "mass": 20,
      "sigma": 0.07,
      "epsilon": -0.1
    },
    {
      "id": 1,
      "mass": 40,
      "sigma": 0.14,
      "epsilon": -0.1
    },
    {
      "id": 2,
      "mass": 60,
      "sigma": 0.21,
      "epsilon": -0.1
    },
    {
      "id": 3,
      "mass": 80,
      "sigma": 0.28,
      "epsilon": -0.1
    },
    {
      "id": 4,
      "mass": 600,
      "sigma": 0.3,
      "epsilon": -5
    }
  ],
  "atoms": {
    "X": [
      0.93
    ],
    "Y": [
      1.26
    ],
    "VX": [
      0.001
    ],
    "VY": [
      0
    ],
    "CHARGE": [
      0
    ],
    "FRICTION": [
      0
    ],
    "ELEMENT": [
      3
    ],
    "PINNED": [
      0
    ]
  },
  "obstacles": {
    "x": [
      3.48
    ],
    "y": [
      0.050000000000000266
    ],
    "height": [
      2.42
    ],
    "width": [
      0.41
    ],
    "density": [
      "Infinity"
    ],
    "color": [
      [
        128,
        128,
        128
      ]
    ],
    "visible": [
      true
    ]
  }
}